SymLinkDB/__init__.py
SymLinkDB/document_code.py
SymLinkDB/test.py
SymLinkDB/parts/cfd_backend/__init__.py
SymLinkDB/parts/cfd_backend/test.py
SymLinkDB/parts/memory_backend/__init__.py
SymLinkDB/parts/memory_backend/test.py
SymLinkDB-0.4.12.dist-info/METADATA
SymLinkDB-0.4.12.dist-info/WHEEL
SymLinkDB-0.4.12.dist-info/top_level.txt
SymLinkDB-0.4.12.dist-info/RECORD
