Metadata-Version: 2.1
Name: SymLinkDB
Version: 0.4.12
Summary: A graph database characterized by bidirectional links. It allows for intuitive design of data relationships.
Home-page: https://github.co.jp/
Author: bib_inf
Author-email: contact.bibinf@gmail.com
License: CC0 v1.0
Classifier: Programming Language :: Python :: 3
Classifier: License :: CC0 1.0 Universal (CC0 1.0) Public Domain Dedication
Requires-Dist: ezpip
Requires-Dist: sout (>=1.2.1)
Requires-Dist: relpath
Requires-Dist: slim-id (>=0.0.2)
Requires-Dist: fies (>=1.4.0)
Requires-Dist: CachedFileDic (>=0.3.0)
